{
  "id": "94778e1c-20f6-4611-95bd-e1cd8b3a96e9",
  "prevId": "00000000-0000-0000-0000-000000000000",
  "version": "7",
  "dialect": "postgresql",
  "tables": {
    "public.game_states": {
      "name": "game_states",
      "schema": "",
      "columns": {
        "id": {
          "name": "id",
          "type": "serial",
          "primaryKey": true,
          "notNull": true
        },
        "player_id": {
          "name": "player_id",
          "type": "varchar(255)",
          "primaryKey": false,
          "notNull": true
        },
        "issue_no": {
          "name": "issue_no",
          "type": "integer",
          "primaryKey": false,
          "notNull": true
        },
        "mode": {
          "name": "mode",
          "type": "varchar(10)",
          "primaryKey": false,
          "notNull": false
        },
        "guesses": {
          "name": "guesses",
          "type": "jsonb",
          "primaryKey": false,
          "notNull": true,
          "default": "'[]'::jsonb"
        },
        "solved": {
          "name": "solved",
          "type": "boolean",
          "primaryKey": false,
          "notNull": true,
          "default": false
        },
        "created_at": {
          "name": "created_at",
          "type": "timestamp",
          "primaryKey": false,
          "notNull": true,
          "default": "now()"
        },
        "updated_at": {
          "name": "updated_at",
          "type": "timestamp",
          "primaryKey": false,
          "notNull": true,
          "default": "now()"
        }
      },
      "indexes": {},
      "foreignKeys": {},
      "compositePrimaryKeys": {},
      "uniqueConstraints": {},
      "policies": {},
      "checkConstraints": {},
      "isRLSEnabled": false
    },
    "public.puzzles": {
      "name": "puzzles",
      "schema": "",
      "columns": {
        "id": {
          "name": "id",
          "type": "serial",
          "primaryKey": true,
          "notNull": true
        },
        "issue_no": {
          "name": "issue_no",
          "type": "integer",
          "primaryKey": false,
          "notNull": true
        },
        "subject_id": {
          "name": "subject_id",
          "type": "integer",
          "primaryKey": false,
          "notNull": true
        },
        "clues": {
          "name": "clues",
          "type": "text[]",
          "primaryKey": false,
          "notNull": true
        },
        "date": {
          "name": "date",
          "type": "timestamp",
          "primaryKey": false,
          "notNull": true
        },
        "created_at": {
          "name": "created_at",
          "type": "timestamp",
          "primaryKey": false,
          "notNull": true,
          "default": "now()"
        }
      },
      "indexes": {},
      "foreignKeys": {
        "puzzles_subject_id_subjects_id_fk": {
          "name": "puzzles_subject_id_subjects_id_fk",
          "tableFrom": "puzzles",
          "tableTo": "subjects",
          "columnsFrom": [
            "subject_id"
          ],
          "columnsTo": [
            "id"
          ],
          "onDelete": "no action",
          "onUpdate": "no action"
        }
      },
      "compositePrimaryKeys": {},
      "uniqueConstraints": {
        "puzzles_issue_no_unique": {
          "name": "puzzles_issue_no_unique",
          "nullsNotDistinct": false,
          "columns": [
            "issue_no"
          ]
        }
      },
      "policies": {},
      "checkConstraints": {},
      "isRLSEnabled": false
    },
    "public.subjects": {
      "name": "subjects",
      "schema": "",
      "columns": {
        "id": {
          "name": "id",
          "type": "serial",
          "primaryKey": true,
          "notNull": true
        },
        "name": {
          "name": "name",
          "type": "varchar(255)",
          "primaryKey": false,
          "notNull": true
        },
        "aliases": {
          "name": "aliases",
          "type": "text[]",
          "primaryKey": false,
          "notNull": false
        },
        "category": {
          "name": "category",
          "type": "varchar(100)",
          "primaryKey": false,
          "notNull": true
        },
        "bio_line": {
          "name": "bio_line",
          "type": "text",
          "primaryKey": false,
          "notNull": false
        },
        "created_at": {
          "name": "created_at",
          "type": "timestamp",
          "primaryKey": false,
          "notNull": true,
          "default": "now()"
        }
      },
      "indexes": {},
      "foreignKeys": {},
      "compositePrimaryKeys": {},
      "uniqueConstraints": {},
      "policies": {},
      "checkConstraints": {},
      "isRLSEnabled": false
    }
  },
  "enums": {},
  "schemas": {},
  "sequences": {},
  "roles": {},
  "policies": {},
  "views": {},
  "_meta": {
    "columns": {},
    "schemas": {},
    "tables": {}
  }
}